migrations/README
migrations/alembic.ini
migrations/env.py
migrations/script.py.mako
migrations/versions/222c027bbdec_file_type.py
migrations/versions/55161145af8f_add_user_recommendations_model.py
migrations/versions/5c34861d9ef9_add_file_to_organization.py
migrations/versions/78c25d669d9c_first_models.py
migrations/versions/9cce5410d6c2_add_user_rating_to_organization.py
migrations/versions/ea52bc400e9b_remove_blob_file_from_db.py
migrations/versions/ff9e18b937bd_.py
motor/__init__.py
motor/adaptors.py
motor/models.py
motor/processor.py
motor/tasks.py
organizations/__init__.py
organizations/models.py
server/__init__.py
server/api/__init__.py
server/api/handlers/__init__.py
server/api/handlers/file_loader.py
server/api/handlers/organizations.py
server/api/handlers/recommendations.py
server/api/handlers/register_all_handlers.py
server/api/handlers/user_ratings.py
server/app.py
server/config.py
server/database.py
server/rebar.py
server/schemas/__init__.py
server/schemas/file_data.py
server/schemas/general.py
server/schemas/organization.py
server/schemas/user_ratings.py
fra-2.4.0.dist-info/LICENSE
fra-2.4.0.dist-info/METADATA
fra-2.4.0.dist-info/WHEEL
fra-2.4.0.dist-info/RECORD
