Metadata-Version: 2.1
Name: fra
Version: 2.4.0
Summary: Simple Recommendation System, content based.
Home-page: https://gitlab.com/elin3t/fra
License: MIT
Author: Eliecer Daza
Requires-Python: >=3.9,<4.0
Classifier: License :: OSI Approved :: MIT License
Classifier: Programming Language :: Python :: 3
Classifier: Programming Language :: Python :: 3.9
Classifier: Programming Language :: Python :: 3.10
Classifier: Programming Language :: Python :: 3.11
Requires-Dist: Flask-CeleryExt (>=0.4.3,<0.5.0)
Requires-Dist: Flask-Migrate (>=3.1.0,<4.0.0)
Requires-Dist: celery (>=5.2.7,<6.0.0)
Requires-Dist: flask-rebar (>=2.2.1,<3.0.0)
Requires-Dist: gunicorn (>=20.1.0,<21.0.0)
Requires-Dist: pandas (>=1.5.0,<2.0.0)
Requires-Dist: psycopg2-binary (>=2.9.5,<3.0.0)
Requires-Dist: redis (>=4.3.4,<5.0.0)
Project-URL: Repository, https://gitlab.com/elin3t/fra
